README.md
setup.cfg
setup.py
distributio/Binomialdistribution.py
distributio/Gaussiandistribution.py
distributio/Generaldistribution.py
distributio/__init__.py
distributio.egg-info/PKG-INFO
distributio.egg-info/SOURCES.txt
distributio.egg-info/dependency_links.txt
distributio.egg-info/not-zip-safe
distributio.egg-info/top_level.txt